{
  "data": {
    "nodeServices": {
      "__typename": "NodeServiceConnection",
      "nodes": [
        {
          "__typename": "NodeService",
          "id": "service-cleaning",
          "title": "Teeth Cleaning & Exams",
          "path": "/services/teeth-cleaning-and-exams",
          "body": {
            "processed": "<p>Regular dental cleanings and comprehensive exams are the foundation of excellent oral health. Our skilled hygienists use the latest techniques and technology to thoroughly clean your teeth while making the experience as comfortable as possible.</p><h2>What to Expect</h2><ul><li>Thorough removal of plaque and tartar buildup</li><li>Professional polishing to remove surface stains</li><li>Comprehensive examination by your dentist</li><li>Digital X-rays as needed (significantly less radiation than traditional X-rays)</li><li>Oral cancer screening</li><li>Personalized oral hygiene recommendations</li></ul><h2>How Often Should You Visit?</h2><p>The American Dental Association recommends professional cleanings every six months for most patients. However, patients with gum disease or certain health conditions may benefit from more frequent visits. Your dentist will recommend a schedule tailored to your individual needs.</p>",
            "summary": "Regular dental cleanings and comprehensive exams are the foundation of excellent oral health. Our skilled hygienists use the latest techniques and technology to thoroughly clean your teeth while makin"
          },
          "image": {
            "url": "https://images.unsplash.com/photo-1588776814546-1ffcf47267a5?w=800&q=80",
            "alt": "Dental hygienist performing a professional teeth cleaning",
            "width": 800,
            "height": 533,
            "variations": [
              {
                "name": "LARGE",
                "url": "https://images.unsplash.com/photo-1588776814546-1ffcf47267a5?w=800&q=80",
                "width": 800,
                "height": 533
              },
              {
                "name": "MEDIUM",
                "url": "https://images.unsplash.com/photo-1588776814546-1ffcf47267a5?w=480&q=80",
                "width": 480,
                "height": 320
              },
              {
                "name": "THUMBNAIL",
                "url": "https://images.unsplash.com/photo-1588776814546-1ffcf47267a5?w=200&q=80",
                "width": 200,
                "height": 133
              }
            ]
          },
          "summary": {
            "processed": "<p>Professional cleanings and comprehensive exams to keep your teeth and gums healthy. Recommended every six months.</p>",
            "summary": "Professional cleanings and comprehensive exams to keep your teeth and gums healthy. Recommended every six months."
          },
          "duration": "60 minutes",
          "priceRange": "$150 - $300",
          "insuranceAccepted": true,
          "serviceCategory": [
            {
              "id": "Preventive Care",
              "name": "Preventive Care"
            }
          ]
        },
        {
          "__typename": "NodeService",
          "id": "service-implants",
          "title": "Dental Implants",
          "path": "/services/dental-implants",
          "body": {
            "processed": "<p>Dental implants are the gold standard for replacing missing teeth. These titanium posts are surgically placed in the jawbone where they fuse naturally with the bone, providing a permanent, stable foundation for replacement teeth that look, feel, and function like natural teeth.</p><h2>Benefits of Dental Implants</h2><ul><li>Look and feel like natural teeth</li><li>Preserve jawbone health and prevent bone loss</li><li>No adhesives or removal required</li><li>Can last a lifetime with proper care</li><li>Eat, speak, and smile with confidence</li></ul><h2>The Implant Process</h2><p>Treatment typically occurs in stages over several months:</p><ul><li><strong>Consultation:</strong> Comprehensive exam including 3D imaging to assess bone density and plan placement</li><li><strong>Placement:</strong> The titanium implant is surgically placed in the jawbone under local anesthesia</li><li><strong>Healing:</strong> 3-6 months for the implant to integrate with the bone (osseointegration)</li><li><strong>Restoration:</strong> A custom crown, bridge, or denture is attached to the implant</li></ul><p>We offer sedation options for patients who experience dental anxiety.</p>",
            "summary": "Dental implants are the gold standard for replacing missing teeth. These titanium posts are surgically placed in the jawbone where they fuse naturally with the bone, providing a permanent, stable foun"
          },
          "image": {
            "url": "https://images.unsplash.com/photo-1609840114035-3c981b782dfe?w=800&q=80",
            "alt": "Close-up of a dental implant model showing placement",
            "width": 800,
            "height": 533,
            "variations": [
              {
                "name": "LARGE",
                "url": "https://images.unsplash.com/photo-1609840114035-3c981b782dfe?w=800&q=80",
                "width": 800,
                "height": 533
              },
              {
                "name": "MEDIUM",
                "url": "https://images.unsplash.com/photo-1609840114035-3c981b782dfe?w=480&q=80",
                "width": 480,
                "height": 320
              },
              {
                "name": "THUMBNAIL",
                "url": "https://images.unsplash.com/photo-1609840114035-3c981b782dfe?w=200&q=80",
                "width": 200,
                "height": 133
              }
            ]
          },
          "summary": {
            "processed": "<p>Permanent tooth replacement that looks, feels, and functions like natural teeth. A long-lasting solution for missing teeth.</p>",
            "summary": "Permanent tooth replacement that looks, feels, and functions like natural teeth. A long-lasting solution for missing teeth."
          },
          "duration": "Multiple visits over 3-6 months",
          "priceRange": "$3,000 - $5,000 per implant",
          "insuranceAccepted": true,
          "serviceCategory": [
            {
              "id": "Restorative",
              "name": "Restorative"
            },
            {
              "id": "Oral Surgery",
              "name": "Oral Surgery"
            }
          ]
        },
        {
          "__typename": "NodeService",
          "id": "service-whitening",
          "title": "Professional Teeth Whitening",
          "path": "/services/teeth-whitening",
          "body": {
            "processed": "<p>Reveal a brighter, more radiant smile with our professional whitening treatments. Whether you prefer the dramatic results of an in-office session or the convenience of a take-home kit, we offer safe and effective solutions tailored to your lifestyle and goals.</p><h2>In-Office Whitening</h2><p>Our in-office treatment uses a professional-strength whitening gel activated by a specialized LED light. In just one hour, you can achieve teeth up to eight shades whiter. This is the perfect choice for patients who want immediate, noticeable results.</p><h2>Take-Home Whitening Kits</h2><p>We create custom-fitted whitening trays from impressions of your teeth, ensuring even contact with the whitening gel and maximum comfort. Wear the trays for 30-60 minutes daily for two weeks for gradual, natural-looking results.</p><h2>Maintaining Your Results</h2><ul><li>Brush twice daily with a whitening toothpaste</li><li>Limit coffee, tea, red wine, and other staining foods</li><li>Schedule touch-up treatments every 6-12 months</li><li>Continue with regular professional cleanings</li></ul>",
            "summary": "Reveal a brighter, more radiant smile with our professional whitening treatments. Whether you prefer the dramatic results of an in-office session or the convenience of a take-home kit, we offer safe a"
          },
          "image": {
            "url": "https://images.unsplash.com/photo-1606265752439-1f18756aa5fc?w=800&q=80",
            "alt": "Patient smiling brightly after teeth whitening treatment",
            "width": 800,
            "height": 533,
            "variations": [
              {
                "name": "LARGE",
                "url": "https://images.unsplash.com/photo-1606265752439-1f18756aa5fc?w=800&q=80",
                "width": 800,
                "height": 533
              },
              {
                "name": "MEDIUM",
                "url": "https://images.unsplash.com/photo-1606265752439-1f18756aa5fc?w=480&q=80",
                "width": 480,
                "height": 320
              },
              {
                "name": "THUMBNAIL",
                "url": "https://images.unsplash.com/photo-1606265752439-1f18756aa5fc?w=200&q=80",
                "width": 200,
                "height": 133
              }
            ]
          },
          "summary": {
            "processed": "<p>Professional-grade whitening treatments for a brighter, more confident smile. In-office and take-home options available.</p>",
            "summary": "Professional-grade whitening treatments for a brighter, more confident smile. In-office and take-home options available."
          },
          "duration": "60 minutes (in-office) or 2 weeks (take-home)",
          "priceRange": "$300 - $600",
          "insuranceAccepted": false,
          "serviceCategory": [
            {
              "id": "Cosmetic",
              "name": "Cosmetic"
            }
          ]
        },
        {
          "__typename": "NodeService",
          "id": "service-invisalign",
          "title": "Invisalign Clear Aligners",
          "path": "/services/invisalign-clear-aligners",
          "body": {
            "processed": "<p>Straighten your teeth discreetly with Invisalign clear aligners. These virtually invisible, removable aligners gradually shift your teeth into the desired position without the brackets and wires of traditional braces.</p><h2>How Invisalign Works</h2><ul><li>We take digital impressions of your teeth using a 3D scanner (no messy molds)</li><li>A custom treatment plan maps out the precise movements of your teeth</li><li>You receive a series of custom aligners, each worn for 1-2 weeks</li><li>You visit our office every 6-8 weeks to monitor progress</li><li>Treatment typically takes 12-18 months for most cases</li></ul><h2>Advantages Over Traditional Braces</h2><ul><li>Nearly invisible when worn</li><li>Removable for eating, drinking, brushing, and flossing</li><li>No food restrictions</li><li>Fewer office visits required</li><li>More comfortable than metal brackets and wires</li></ul><p>As a certified Invisalign provider, Dr. Patel has successfully treated over 300 patients with clear aligner therapy.</p>",
            "summary": "Straighten your teeth discreetly with Invisalign clear aligners. These virtually invisible, removable aligners gradually shift your teeth into the desired position without the brackets and wires of tr"
          },
          "image": {
            "url": "https://images.unsplash.com/photo-1598256989800-fe5f95da9787?w=800&q=80",
            "alt": "Clear dental aligners held in hand",
            "width": 800,
            "height": 533,
            "variations": [
              {
                "name": "LARGE",
                "url": "https://images.unsplash.com/photo-1598256989800-fe5f95da9787?w=800&q=80",
                "width": 800,
                "height": 533
              },
              {
                "name": "MEDIUM",
                "url": "https://images.unsplash.com/photo-1598256989800-fe5f95da9787?w=480&q=80",
                "width": 480,
                "height": 320
              },
              {
                "name": "THUMBNAIL",
                "url": "https://images.unsplash.com/photo-1598256989800-fe5f95da9787?w=200&q=80",
                "width": 200,
                "height": 133
              }
            ]
          },
          "summary": {
            "processed": "<p>Straighten your teeth discreetly with custom clear aligners. Virtually invisible, removable, and comfortable.</p>",
            "summary": "Straighten your teeth discreetly with custom clear aligners. Virtually invisible, removable, and comfortable."
          },
          "duration": "12-18 months total treatment",
          "priceRange": "$3,500 - $7,000",
          "insuranceAccepted": true,
          "serviceCategory": [
            {
              "id": "Orthodontics",
              "name": "Orthodontics"
            },
            {
              "id": "Cosmetic",
              "name": "Cosmetic"
            }
          ]
        }
      ]
    }
  }
}